{"options":{"validator":{"$jsonSchema":{"bsonType":"object","required":["orderId","productId","quantity","unitPriceSnapshot","lineTotal"],"properties":{"orderId":{"bsonType":"objectId"},"productId":{"bsonType":"objectId"},"productNameSnapshot":{"bsonType":"string"},"quantity":{"bsonType":["int","long","double","decimal"]},"unitPriceSnapshot":{"bsonType":["int","long","double","decimal"]},"lineTotal":{"bsonType":["int","long","double","decimal"]}}}},"validationLevel":"moderate","validationAction":"error"},"indexes":[{"v":{"$numberInt":"2"},"key":{"_id":{"$numberInt":"1"}},"name":"_id_"},{"v":{"$numberInt":"2"},"key":{"orderId":{"$numberInt":"1"}},"name":"ix_order_items_order"}],"uuid":"a9cbbf4210d245e89d83b09fae74213f","collectionName":"orderItems","type":"collection"}